Workbook
Name Aporte: Investimento!$D$13:$D$13
Name Dividendos_mensais: Investimento!$D$17:$D$17
Name Patrimonio: Investimento!$D$16:$D$16
Name Patrimonio_2anos: Investimento!$C$20:$C$20
Name Porcent_mes: Investimento!$D$9:$D$9
Name Qte_anos: Investimento!$D$14:$D$14
Name Rendimento_carteira: Investimento!$D$8:$D$8
Name Salario: Investimento!$D$7:$D$7
Name Sugestao_investimento: Investimento!$D$10:$D$10
Name Taxa_rendimento: Investimento!$D$15:$D$15

Sheet Investimento
B6: CONFIGURAÇÕES
B7: Salario | D7: 3000
B8: Rendimento carteira | D8: 0.01
B9: % Investimento por mês | D9: 0.25
B10: Sugestão de investimento | D10: {=Salario*Porcent_mes} -> 750
B12: INVESTIMENTO MENSAL
B13: Quanto investir por mês ? | D13: {=Sugestao_investimento} -> 750
B14: Por quanto anos ? | D14: 5
B15: Taxa de rendimento mensal ? | D15: 0.0108
B16: Patrimônio acumulado ? | D16: {=FV(Taxa_rendimento,Qte_anos*12,Aporte*-1)} -> 62853.015
B17: Dividendos mensais ? | D17: {=Patrimonio*1%} -> 628.53015
B19: CENÁRIOS | D19: DIVIDENDO
A20: 2 | B20: Quanto em 2 anos ? | C20: {=FV(Taxa_rendimento,A20*12,Aporte*-1)} -> 20423.148 | D20: =C20*1% -> 204.23148
A21: 5 | B21: Quantos em 5 anos ? | C21: {=FV(Taxa_rendimento,A21*12,Aporte*-1)} -> 62853.015 | D21: =C21*1% -> 628.53015
A22: 10 | B22: Quanto em 10 anos ? | C22: {=FV(Taxa_rendimento,A22*12,Aporte*-1)} -> 182593.25 | D22: =C22*1% -> 1825.9325
A23: 20 | B23: Quanto em 20 anos ? | C23: {=FV(Taxa_rendimento,A23*12,Aporte*-1)} -> 845286.74 | D23: =C23*1% -> 8452.8674
A24: 30 | B24: Quanto em 30 anos ? | C24: {=FV(Taxa_rendimento,A24*12,Aporte*-1)} -> 3250428.6 | D24: =C24*1% -> 32504.286
B26: PERFIL | D26: Conservador
B27: VALOR APORTE POR MÊS | D27: {=Aporte} -> 750
B29: TIPO DE FII | C29: % SUGERIDO | D29: VALORES
B30: PAPEL | C30: =VLOOKUP($D$26&"-"&B30,Repor!$A:$D,4,FALSE) -> 0.3 | D30: =$D$27*C30 -> 225
B31: TIJOLO | C31: =VLOOKUP($D$26&"-"&B31,Repor!$A:$D,4,FALSE) -> 0.5 | D31: =$D$27*C31 -> 375
B32: HIBRIDOS | C32: =VLOOKUP($D$26&"-"&B32,Repor!$A:$D,4,FALSE) -> 0.1 | D32: =$D$27*C32 -> 75
B33: FOFs | C33: =VLOOKUP($D$26&"-"&B33,Repor!$A:$D,4,FALSE) -> 0.1 | D33: =$D$27*C33 -> 75
B34: DESENVOLVIMENTO | C34: =VLOOKUP($D$26&"-"&B34,Repor!$A:$D,4,FALSE) -> 0 | D34: =$D$27*C34 -> 0
B35: HOTELARIAS | C35: =VLOOKUP($D$26&"-"&B35,Repor!$A:$D,4,FALSE) -> 0 | D35: =$D$27*C35 -> 0
B36: TOTAL | D36: =SUM(D30:D35) -> 750

Sheet Repor
A2: CHAVE | B2: PERFIL | C2: TIPO DE FII | D2: PERCENTUAL
A3: =B3&"-"&Repor!C3 -> Conservador-PAPEL | B3: Conservador | C3: PAPEL | D3: 0.3
A4: =B4&"-"&Repor!C4 -> Conservador-TIJOLO | B4: Conservador | C4: TIJOLO | D4: 0.5
A5: =B5&"-"&Repor!C5 -> Conservador-HIBRIDOS | B5: Conservador | C5: HIBRIDOS | D5: 0.1
A6: =B6&"-"&Repor!C6 -> Conservador-FOFs | B6: Conservador | C6: FOFs | D6: 0.1
A7: =B7&"-"&Repor!C7 -> Conservador-DESENVOLVIMENTO | B7: Conservador | C7: DESENVOLVIMENTO | D7: 0
A8: =B8&"-"&Repor!C8 -> Conservador-HOTELARIAS | B8: Conservador | C8: HOTELARIAS | D8: 0
A9: =B9&"-"&Repor!C9 -> Moderado-PAPEL | B9: Moderado | C9: PAPEL | D9: 0.32
A10: =B10&"-"&Repor!C10 -> Moderado-TIJOLO | B10: Moderado | C10: TIJOLO | D10: 0.35
A11: =B11&"-"&Repor!C11 -> Moderado-HIBRIDOS | B11: Moderado | C11: HIBRIDOS | D11: 0.08
A12: =B12&"-"&Repor!C12 -> Moderado-FOFs | B12: Moderado | C12: FOFs | D12: 0.05
A13: =B13&"-"&Repor!C13 -> Moderado-DESENVOLVIMENTO | B13: Moderado | C13: DESENVOLVIMENTO | D13: 0.1
A14: =B14&"-"&Repor!C14 -> Moderado-HOTELARIAS | B14: Moderado | C14: HOTELARIAS | D14: 0.1
... A20: =B20&"-"&Repor!C20 -> Agressivo-HOTELARIAS | B20: Agressivo | C20: HOTELARIAS | D20: 0.1
